[
  {
    "description": "Chợ nổi Cái Răng là chợ nổi chuyên trao đổi, mua bán nông sản, các loại trái cây, hàng hóa, thực phẩm, ăn uống ở trên sông và là điểm tham quan đặc sắc của quận Cái Răng, thành phố Cần Thơ. Wikipedia",
    "images": [
      "09df0e94-3954-48ed-955f-f9a924e68533.jpg",
      "161bef08-da8d-44a0-b647-15a25cd8f190.jpg",
      "027dce0e-5e7b-4e22-a4a2-6bd0cc731f3c.jpg"
    ],
    "title": "Chợ Nổi Cái Răng"
  },
  {
    "description": "Bảo tàng lớn với các hiện vật lịch sử",
    "images": [
      "30415a84-c331-4237-b274-db6eb6f2f9cb.jpg",
      "a000a421-2592-4a10-85e9-ffcc74def0d8.jpg",
      "7ee1e30c-570a-4525-9830-4d940af60284.jpg"
    ],
    "title": "Bảo Tàng thành phố Cần Thơ"
  },
  {
    "description": "Khu nghỉ dưỡng xanh mát có vườn & các hoạt động",
    "images": [
      "0d8e7b71-2ad7-49f6-bb61-a9d177d90fe4.jpg",
      "a243e5ca-74b1-4758-9201-90afc46cea88.jpg",
      "d5a43996-991a-4a82-9b4a-b7c0e4b50151.jpg"
    ],
    "title": "Làng Du lịch Mỹ Khánh"
  },
  {
    "description": "Chùa Ông (Cần Thơ), tên gốc là Quảng Triệu Hội Quán; tọa lạc tại số 32 đường Hai Bà Trưng, thuộc phường Tân An, quận Ninh Kiều, thành phố Cần Thơ, Việt Nam. Đây là một ngôi chùa của người Hoa gốc Quảng Đông tại Cần Thơ, và là một di tích lịch sử cấp quốc gia kể từ năm 1993. Wikipedia",
    "images": [
      "11a1b9dc-96a9-4352-ab99-b5607a6aff32.jpg",
      "a5bcc050-2a77-4739-9589-6abde5c91c2a.jpg",
      "7ab8da57-e83f-41b9-b035-4e8813da5a3f.jpg"
    ],
    "title": "Chùa Ông"
  },
  {
    "description": "Nhà cổ xinh đẹp do người Pháp xây dựng",
    "images": [
      "f5085183-b50f-4103-81a5-81e2bb876239.jpg",
      "c68bb64f-951f-41df-869a-1faedb960952.jpg",
      "72aea480-8279-461b-8eee-98b97f27505d.jpg"
    ],
    "title": "Nhà cổ Bình Thủy"
  },
  {
    "description": "Cầu Cần Thơ là cây cầu bắc qua sông Hậu, nối liền quận Cái Răng, thành phố Cần Thơ và thị xã Bình Minh, tỉnh Vĩnh Long. Cầu Cần Thơ là cầu dây văng lớn nhất Việt Nam tính đến hiện tại. Wikipedia",
    "images": [
      "7983f6f0-7343-43ec-a338-4607a89a9959.jpg",
      "aeb04a36-be96-4615-8831-d374bce0304d.jpg",
      "97796e32-4765-40a1-9d8f-56ec4afe4434.jpg"
    ],
    "title": "Cầu Cần Thơ"
  },
  {
    "description": "Thiền viện Trúc Lâm Phương Nam tọa lạc tại ấp Mỹ Nhơn, xã Mỹ Khánh, huyện Phong Điền, thành phố Cần Thơ, Việt Nam. Đây là một thiền viện thuộc hàng lớn nhất ở miền Tây Nam Bộ, tính đến thời điểm năm 2014. Thiền viện được khởi công xây dựng vào ngày 16 tháng 7 năm 2013, trên một diện tích 38.016 m². Sau nhiều tháng thi công, thiền viện đã được khánh thành vào ngày 17 tháng 5 năm 2014. Chánh điện lợp ngói tám mái theo theo phong cách nhà Trần. Tổ điện lợp ngói bốn mái theo phong cách nhà Lý. Lầu trống và Gác chuông được làm theo kiểu tháp chuông chùa Keo ở tỉnh Thái Bình. Đáng chú ý, phần gỗ trong 4 hạng mục này đều là gỗ lim được nhập từ Nam Phi. Bên trong chánh điện, ở giữa là tượng Phật Thích Ca bằng đồng nặng 3, 5 tấn, tạc ở tư thế ngồi và tay cầm cành hoa; hai bên là tượng Bồ tát Phổ Hiền và Bồ tát Văn Thù. Bên trong Tổ điện là tượng Tổ Bồ Đề Đạt Ma và Trúc Lâm Tam Tổ. Ngoài tượng Phật Thích Ca là được đúc bằng đồng, các tượng thờ khác ở đây đều được bằng tạc bằng gỗ du sam đá vôi có tuổi thọ khoảng 800 năm.",
    "images": [
      "cc253018-524b-4938-96e5-65e4fc4be653.jpg",
      "7dd86635-a801-403e-9c79-d6858297ac58.jpg",
      "2519cf0b-c271-400f-a621-793238f14c29.jpg"
    ],
    "title": "Thiền viện Trúc Lâm Phương Nam"
  },
  {
    "description": "Đảo",
    "images": [
      "b34289fd-a156-41e8-af2f-ba4bcea4ddfb.jpg",
      "4467fd4b-af94-47f9-9006-319146de5e51.jpg",
      "05a089df-88c8-40df-86c7-df499f2db2ff.jpg"
    ],
    "title": "Cồn Sơn"
  },
  {
    "description": "Chùa Nam Nhã; tọa lạc ở số 612, đường Cách mạng Tháng Tám, thuộc phường Bùi Hữu Nghĩa, quận Bình Thủy, thành phố Cần Thơ. Chùa trực thuộc Giáo hội Phật Đường Nam Tông Minh Sư Đạo. Ngôi chùa không chỉ đẹp bởi lối kiến trúc, mà còn bởi lịch sử của chùa gắn liền với nhiều hoạt động yêu nước của một số sĩ phu và người dân Việt Nam. Ngày 25 tháng 1 năm 1991, chùa Nam Nhã đã được công nhận là Di tích Lịch sử cấp Quốc gia. Wikipedia",
    "images": [
      "1439c787-af59-4898-a306-5764e084a622.jpg",
      "780c5cd8-8b2f-4f95-8b4f-f7f24896f3a4.jpg",
      "911ac96d-3ce0-42ee-97ba-b0a70a09982c.jpg"
    ],
    "title": "Chùa Nam Nhã"
  },
  {
    "description": "Đình Bình Thủy, tên chữ là Long Tuyền Cổ Miếu là một đình thần tại Thành phố Cần Thơ. Đây là một công trình có giá trị về kiến trúc nghệ thuật cổ truyền của người Việt giai đoạn khai hoang miền Tây Nam Bộ. Wikipedia",
    "images": [
      "7ba94a0d-2cb0-4cd6-a582-2f5fdf460904.jpg",
      "5725f460-2f66-4873-83c5-af86916983e9.jpg",
      "e37d720c-2524-4d2d-94fd-a2d61987ed2f.jpg"
    ],
    "title": "Đình Bình Thủy"
  },
  {
    "description": "Đảo",
    "images": [
      "4ac33706-e3eb-4741-904d-4cd352d34093.jpg",
      "5c0ee795-03c0-4a43-bb10-b8c6da55ab6c.jpg",
      "8081b20b-798c-43a9-ae10-041232c81872.jpg"
    ],
    "title": "Cồn Khương"
  },
  {
    "description": "Công viên có đường đi bộ bên sông",
    "images": [
      "c41e3814-b01b-43fd-8303-75cef806dec5.jpg",
      "89a8467f-85e8-47a7-b4ce-548e9adf28b3.jpg",
      "90e53244-d9e8-4ae6-a8ff-a141046c2798.jpg"
    ],
    "title": "Công Viên Bến Ninh Kiều"
  },
  {
    "description": "Điểm thu hút khách du lịch",
    "images": [
      "dedea41c-8573-43bf-9339-f8863ef61de7.jpg",
      "26013d3d-2039-4ddd-ab38-75026e5473e8.jpg",
      "e753ea02-01d5-44c6-8c24-a66c4cca480a.jpg"
    ],
    "title": "Chợ Cần Thơ"
  },
  {
    "description": "Chợ",
    "images": [
      "ee334ac3-fb2c-496f-a85f-d64b3a87a0cb.jpg",
      "7cc1687c-6c08-4b01-9679-5155b5fcdde1.jpg",
      "a221911c-9741-4c58-984a-b5db1cad31d2.jpg"
    ],
    "title": "Chợ Đêm Cần Thơ"
  },
  {
    "description": "Trung tâm thông tin cho khách",
    "images": [
      "99f5cebc-7149-47d4-9886-87e98ceb3d90.jpg",
      "26419d2d-e55e-46d6-9f45-3b00b3550ed4.jpg",
      "27a681a2-8f55-4601-8328-91daabfa974a.jpg"
    ],
    "title": "Công Ty Cổ Phần Du Lịch Cần Thơ"
  },
  {
    "description": "Chợ",
    "images": [
      "3c1cf48e-1201-405b-9ac4-5e70345fe773.jpg",
      "9c30508a-f4ee-40bf-82df-c2b618a7adbe.jpg",
      "5a058c52-eada-4400-9dea-fe1fcae4fdf1.jpg"
    ],
    "title": "Chợ Đêm Ninh Kiều"
  },
  {
    "description": "Cầu",
    "images": [
      "e39faab2-ab82-4d89-acaf-e4ee1271f2c8.jpg",
      "0f7ad446-e267-4032-97b6-76be0ca421b2.jpg",
      "a95b585e-644f-4896-b717-b0e747e98a3f.jpg"
    ],
    "title": "Cầu Ông Đề"
  },
  {
    "description": "Chợ",
    "images": [
      "6945674f-146f-49bc-99c5-7e9ff8fe37a0.jpg",
      "bdfcb691-a6a7-4859-a4f2-e449411dde50.jpg",
      "22259ced-0cec-49bf-bb4e-bcd2c19201a8.jpg"
    ],
    "title": "Chợ Cái Khế/Cai Khe Maket"
  },
  {
    "description": "Điểm thu hút khách du lịch",
    "images": [
      "891ec20d-b5e6-40ce-b3ee-45f957f3e162.jpg",
      "aa755862-7504-4c95-b999-5db45de7aa49.jpg",
      "f584cab5-116d-442d-8970-29a7714d4842.jpg"
    ],
    "title": "Khu Du Lịch Sinh Thái Ông Đề"
  },
  {
    "description": "Công viên",
    "images": [
      "25ef1805-4274-4f4f-9b6f-44b0f2aa03b0.jpg",
      "c5628c40-ee92-4b62-a729-c8c1a1e584c6.jpg",
      "600ac596-f414-4925-bead-3f6ae78a77eb.jpg"
    ],
    "title": "Công viên Lưu Hữu Phước"
  },
  {
    "description": "Điểm thu hút khách du lịch",
    "images": [
      "183cd082-ab52-4f75-a11d-553645e17d47.jpg",
      "6c4fe768-5cfb-440b-8e10-9fed743b86b5.jpg",
      "89a1a2d1-7273-489d-8cf1-566415e799d0.jpg"
    ],
    "title": "Cầu tình yêu Cần Thơ"
  },
  {
    "description": "Điểm thu hút khách du lịch",
    "images": [
      "0385d694-4740-4a20-804b-46bfdf3dc7ef.jpg",
      "b7d313ee-8420-4d36-966e-964bbc521aae.jpg",
      "653b59b8-258a-4f31-829d-5767a1eac43b.jpg"
    ],
    "title": "Bao Gia Trang Vien - The Green resort"
  },
  {
    "description": "Công viên",
    "images": [
      "77e17acc-e579-4a87-b565-61c16695a7d5.jpg",
      "69db4dc1-60b7-4846-bf64-e70acd68fa6e.jpg",
      "46bb98e7-4b73-4017-8c1b-1e7137353459.jpg"
    ],
    "title": "Công viên Văn hóa Miền Tây"
  },
  {
    "description": "Phật giáo và Đền",
    "images": [
      "4c224d9c-3bbd-4a57-bb9d-023a75a2ff99.jpg",
      "faaccc9c-a5ed-415b-8158-00a3bd6f89bc.jpg",
      "6afdb3e8-854b-4087-896e-dafd4a6bbf87.jpg"
    ],
    "title": "Chùa Phật Học"
  },
  {
    "description": "Chùa",
    "images": [
      "cb6869dd-61d7-44c3-894d-25a45eb246df.jpg",
      "7ebf34bf-68e9-4ade-a934-abffe8ca5e29.jpg",
      "8538b865-675f-4536-979b-a9cbe8dca356.jpg"
    ],
    "title": "Chùa Thới Long Cổ Tự"
  },
  {
    "description": "Chùa phật giáo",
    "images": [
      "068181ac-cb88-4ea5-a790-fd1c32d0231e.jpg",
      "3f15c747-208b-4023-b042-5c8ad2a7baeb.jpg",
      "5e771c4a-05e8-40c1-a4c8-85d68952e4dc.jpg"
    ],
    "title": "Chùa Khmer Munirensay - វត្ត មុនីរង្សី"
  },
  {
    "description": "Bãi biển công cộng",
    "images": [
      "2276bcc3-e965-4d74-914c-55ea539440d5.jpg",
      "a1882d38-645d-4db7-b2ea-4e0b225cb28d.jpg",
      "04ed6a37-ab38-4d1c-80ce-8198bc567d8f.jpg"
    ],
    "title": "Bãi Tắm Cần Thơ"
  },
  {
    "description": "Viện bảo tàng",
    "images": [
      "99dc021a-df74-46ca-9886-91926c585658.jpg",
      "945b00c0-20b5-4c7b-ae67-3e681f923a23.jpg",
      "bf490c90-190f-49c2-813b-af813057cf11.jpg"
    ],
    "title": "Bảo Tàng Quân Khu 9"
  },
  {
    "description": "Nhà thờ Công giáo",
    "images": [
      "64c79f5a-3681-459a-8903-4d16d1ceab22.jpg",
      "82c8d16b-140d-4ce1-b854-b352ed75c1d0.jpg",
      "07e86525-91ab-4027-a92d-97faf4eb8b17.jpg"
    ],
    "title": "Nhà thờ chính toà Thánh Tâm Chúa Giê-su - Giáo phận Cần Thơ"
  },
  {
    "description": "Nhà thờ Công giáo",
    "images": [
      "b549dcb2-4b73-40bb-9e4a-9ea09f8598b6.jpg",
      "126af608-4e4f-4b7c-8596-3a51d3738f5d.jpg",
      "c0166594-0da4-4817-949e-776ad940cd9f.jpg"
    ],
    "title": "Nhà thờ Giáo xứ An Hoà"
  },
  {
    "description": "Điểm thu hút khách du lịch",
    "images": [
      "d9174300-e358-4210-b84a-9a8b08754627.jpg",
      "edd5e291-bf88-4160-9f41-a8ee251d0ee6.jpg",
      "c9e43911-41fa-4bd1-b25b-3abfc1dab9ce.jpg"
    ],
    "title": "Du Lịch Cồn Sơn"
  },
  {
    "description": "Điểm quan tâm",
    "images": [],
    "title": "THÁM HIỂM MEKONG"
  },
  {
    "description": "Viện bảo tàng",
    "images": [],
    "title": "Museum of Tarot - Bảo Tàng Tarot"
  },
  {
    "description": "Chợ",
    "images": [],
    "title": "Central Market"
  },
  {
    "description": "Điểm quan tâm",
    "images": [],
    "title": "Mekong Rustic Cần Thơ"
  },
  {
    "description": "Điểm quan tâm",
    "images": [],
    "title": "Thuê xe Cần Thơ giá rẻ Thiên Triều"
  }
]